{
  "file": "personalcabinet_report_Ranjirb_i-5484_t-1.html",
  "university": "Ректор КГТУ им. И.Раззакова",
  "director": "Чыныбаев М. К.",
  "program": "Строительство [Теплогазоснабжение, вентиляция и зеленые технологии] ( Очная бакалавр)(Кыргызский инженерно-строительный институт им. Н. Исанова)",
  "plan": "План набора абитуриентов по специальности: 33 .",
  "recommended": "Рекомендовано: ______. Подтверждено: 23",
  "confirmed": null,
  "total_places": "1-тур. Итого вакантных мест: 33 . Зарегистрированных: 24 .",
  "total_registered": null,
  "admitted_count": 24,
  "not_admitted_count": 0,
  "tables": [
    {
      "header": "Бишкек: 11",
      "records": [
        {
          "num": "1",
          "certificate": "5201082",
          "note": null,
          "main_score": "174",
          "extra_score": "83",
          "total_score": "257",
          "category": "Бишкек",
          "date": "16.07.2025 08:27:54",
          "admitted": true
        },
        {
          "num": "2",
          "certificate": "5200207",
          "note": null,
          "main_score": "171",
          "extra_score": "76",
          "total_score": "247",
          "category": "Бишкек",
          "date": "14.07.2025 11:31:08",
          "admitted": true
        },
        {
          "num": "3",
          "certificate": "5201632",
          "note": null,
          "main_score": "154",
          "extra_score": "76",
          "total_score": "230",
          "category": "Бишкек",
          "date": "14.07.2025 09:56:28",
          "admitted": true
        },
        {
          "num": "4",
          "certificate": "5211803",
          "note": null,
          "main_score": "120",
          "extra_score": "65",
          "total_score": "185",
          "category": "Бишкек",
          "date": "14.07.2025 11:44:13",
          "admitted": true
        },
        {
          "num": "5",
          "certificate": "5230234",
          "note": null,
          "main_score": "146",
          "extra_score": "0",
          "total_score": "146",
          "category": "Бишкек",
          "date": "16.07.2025 13:53:54",
          "admitted": true
        },
        {
          "num": "6",
          "certificate": "5211009",
          "note": null,
          "main_score": "125",
          "extra_score": "0",
          "total_score": "125",
          "category": "Бишкек",
          "date": "16.07.2025 13:26:00",
          "admitted": true
        },
        {
          "num": "7",
          "certificate": "5200944",
          "note": null,
          "main_score": "122",
          "extra_score": "0",
          "total_score": "122",
          "category": "Бишкек",
          "date": "14.07.2025 22:52:41",
          "admitted": true
        },
        {
          "num": "8",
          "certificate": "5222160",
          "note": null,
          "main_score": "114",
          "extra_score": "0",
          "total_score": "114",
          "category": "Бишкек",
          "date": "16.07.2025 13:38:31",
          "admitted": true
        }
      ]
    },
    {
      "header": "Малый город: 2.75",
      "records": [
        {
          "num": "1",
          "certificate": "5960444",
          "note": "Инвалид детства",
          "main_score": "147",
          "extra_score": "68",
          "total_score": "215",
          "category": "Малый город",
          "date": "14.07.2025 09:43:46",
          "admitted": true
        },
        {
          "num": "2",
          "certificate": "5700628",
          "note": null,
          "main_score": "125",
          "extra_score": "0",
          "total_score": "125",
          "category": "Малый город",
          "date": "16.07.2025 13:35:20",
          "admitted": true
        }
      ]
    },
    {
      "header": "Село: 12.38",
      "records": [
        {
          "num": "1",
          "certificate": "5560462",
          "note": null,
          "main_score": "161",
          "extra_score": "113",
          "total_score": "274",
          "category": "Село",
          "date": "16.07.2025 11:44:33",
          "admitted": true
        },
        {
          "num": "2",
          "certificate": "5950757",
          "note": null,
          "main_score": "158",
          "extra_score": "61",
          "total_score": "219",
          "category": "Село",
          "date": "14.07.2025 17:35:52",
          "admitted": true
        },
        {
          "num": "3",
          "certificate": "5380368",
          "note": null,
          "main_score": "144",
          "extra_score": "68",
          "total_score": "212",
          "category": "Село",
          "date": "14.07.2025 10:15:23",
          "admitted": true
        },
        {
          "num": "4",
          "certificate": "5830349",
          "note": null,
          "main_score": "190",
          "extra_score": "0",
          "total_score": "190",
          "category": "Село",
          "date": "14.07.2025 12:35:07",
          "admitted": true
        },
        {
          "num": "5",
          "certificate": "5750144",
          "note": null,
          "main_score": "159",
          "extra_score": "0",
          "total_score": "159",
          "category": "Село",
          "date": "16.07.2025 12:22:36",
          "admitted": true
        },
        {
          "num": "6",
          "certificate": "5121121",
          "note": null,
          "main_score": "138",
          "extra_score": "0",
          "total_score": "138",
          "category": "Село",
          "date": "16.07.2025 11:14:35",
          "admitted": true
        },
        {
          "num": "7",
          "certificate": "5820166",
          "note": null,
          "main_score": "138",
          "extra_score": "0",
          "total_score": "138",
          "category": "Село",
          "date": "16.07.2025 11:46:04",
          "admitted": true
        },
        {
          "num": "8",
          "certificate": "5360086",
          "note": null,
          "main_score": "131",
          "extra_score": "0",
          "total_score": "131",
          "category": "Село",
          "date": "16.07.2025 13:01:15",
          "admitted": true
        },
        {
          "num": "9",
          "certificate": "5340043",
          "note": null,
          "main_score": "120",
          "extra_score": "0",
          "total_score": "120",
          "category": "Село",
          "date": "15.07.2025 13:28:25",
          "admitted": true
        }
      ]
    },
    {
      "header": "Высокогорье: 6.88",
      "records": [
        {
          "num": "1",
          "certificate": "5620014",
          "note": null,
          "main_score": "161",
          "extra_score": "83",
          "total_score": "244",
          "category": "Высокогорье",
          "date": "14.07.2025 11:52:35",
          "admitted": true
        },
        {
          "num": "2",
          "certificate": "5630259",
          "note": null,
          "main_score": "125",
          "extra_score": "68",
          "total_score": "193",
          "category": "Высокогорье",
          "date": "14.07.2025 14:15:48",
          "admitted": true
        },
        {
          "num": "3",
          "certificate": "5550036",
          "note": null,
          "main_score": "117",
          "extra_score": "72",
          "total_score": "189",
          "category": "Высокогорье",
          "date": "16.07.2025 13:58:06",
          "admitted": true
        },
        {
          "num": "4",
          "certificate": "5630384",
          "note": null,
          "main_score": "150",
          "extra_score": "0",
          "total_score": "150",
          "category": "Высокогорье",
          "date": "16.07.2025 13:55:19",
          "admitted": true
        },
        {
          "num": "5",
          "certificate": "5630143",
          "note": null,
          "main_score": "142",
          "extra_score": "0",
          "total_score": "142",
          "category": "Высокогорье",
          "date": "16.07.2025 13:53:14",
          "admitted": true
        }
      ]
    }
  ]
}