{
  "file": "personalcabinet_report_Ranjirk_i-784_t-1.html",
  "university": "Ректор ИГУ им. К.Тыныстанова",
  "director": "Иманбаев А.А",
  "program": "Филологическое образование [Кыргызский язык и литература] (Заочное)(ЦДиПК)",
  "plan": "План набора абитуриентов по специальности: 0 .",
  "recommended": null,
  "confirmed": null,
  "total_places": "1-тур. Итого вакантных мест: 0 . Зарегистрированных: 1 .",
  "total_registered": null,
  "tables": [
    {
      "header": null,
      "records": [
        {
          "num": "1",
          "certificate": "(Реком) 5550545",
          "main_score": "124",
          "extra_score": "0",
          "total_score": "124",
          "category": "Село",
          "date": "15.07.2025 20:27:25"
        }
      ]
    }
  ]
}