{
  "file": "personalcabinet_report_Ranjirk_i-6468_t-1.html",
  "university": "Ректор ОшГУ",
  "director": "Кожобеков К. Г.",
  "program": "Государственное и муниципальное управление [Государственное и муниципальное управление] ( Очная бакалавр)(ИЭБМ)",
  "plan": "План набора абитуриентов по специальности: 75 .",
  "recommended": null,
  "confirmed": null,
  "total_places": "1-тур. Итого вакантных мест: 75 . Зарегистрированных: 43 .",
  "total_registered": null,
  "tables": [
    {
      "header": null,
      "records": [
        {
          "num": "1",
          "certificate": "(Реком) 5760618",
          "main_score": "158",
          "extra_score": "105",
          "total_score": "263",
          "category": "Село",
          "date": "15.07.2025 10:10:32"
        },
        {
          "num": "2",
          "certificate": "(Реком) 5770071",
          "main_score": "160",
          "extra_score": "76",
          "total_score": "236",
          "category": "Высокогорье",
          "date": "14.07.2025 10:00:05"
        },
        {
          "num": "3",
          "certificate": "(Реком) 5760939",
          "main_score": "164",
          "extra_score": "68",
          "total_score": "232",
          "category": "Село",
          "date": "15.07.2025 15:48:17"
        },
        {
          "num": "4",
          "certificate": "(Реком) 5750098",
          "main_score": "141",
          "extra_score": "83",
          "total_score": "224",
          "category": "Село",
          "date": "15.07.2025 15:32:01"
        },
        {
          "num": "5",
          "certificate": "(Реком) 5730396",
          "main_score": "145",
          "extra_score": "79",
          "total_score": "224",
          "category": "Село",
          "date": "15.07.2025 23:47:38"
        },
        {
          "num": "6",
          "certificate": "(Реком) 5410218",
          "main_score": "144",
          "extra_score": "72",
          "total_score": "216",
          "category": "Село",
          "date": "15.07.2025 12:04:27"
        },
        {
          "num": "7",
          "certificate": "(Реком) 5761180",
          "main_score": "135",
          "extra_score": "79",
          "total_score": "214",
          "category": "Село",
          "date": "16.07.2025 11:49:18"
        },
        {
          "num": "8",
          "certificate": "(Реком) 5730462",
          "main_score": "138",
          "extra_score": "72",
          "total_score": "210",
          "category": "Село",
          "date": "14.07.2025 14:09:55"
        },
        {
          "num": "9",
          "certificate": "(Реком) 5121190",
          "main_score": "142",
          "extra_score": "68",
          "total_score": "210",
          "category": "Село",
          "date": "15.07.2025 17:45:08"
        },
        {
          "num": "10",
          "certificate": "(Реком) 5120531",
          "main_score": "144",
          "extra_score": "65",
          "total_score": "209",
          "category": "Село",
          "date": "14.07.2025 09:41:57"
        },
        {
          "num": "11",
          "certificate": "(Реком) 5731089",
          "main_score": "128",
          "extra_score": "79",
          "total_score": "207",
          "category": "Село",
          "date": "14.07.2025 10:20:34"
        },
        {
          "num": "12",
          "certificate": "(Реком) 5330382",
          "main_score": "143",
          "extra_score": "61",
          "total_score": "204",
          "category": "Село",
          "date": "16.07.2025 12:38:27"
        },
        {
          "num": "13",
          "certificate": "(Реком) 5701663",
          "main_score": "135",
          "extra_score": "68",
          "total_score": "203",
          "category": "Село",
          "date": "15.07.2025 13:30:58"
        },
        {
          "num": "14",
          "certificate": "(Реком) 5300021",
          "main_score": "129",
          "extra_score": "72",
          "total_score": "201",
          "category": "Малый город",
          "date": "16.07.2025 10:36:04"
        },
        {
          "num": "15",
          "certificate": "(Реком) 5120703",
          "main_score": "121",
          "extra_score": "79",
          "total_score": "200",
          "category": "Село",
          "date": "14.07.2025 11:19:29"
        },
        {
          "num": "16",
          "certificate": "(Реком) 5700580",
          "main_score": "135",
          "extra_score": "65",
          "total_score": "200",
          "category": "Малый город",
          "date": "14.07.2025 23:52:51"
        },
        {
          "num": "17",
          "certificate": "(Реком) 5760787",
          "main_score": "116",
          "extra_score": "83",
          "total_score": "199",
          "category": "Село",
          "date": "14.07.2025 18:21:30"
        },
        {
          "num": "18",
          "certificate": "(Реком) 5702090",
          "main_score": "118",
          "extra_score": "79",
          "total_score": "197",
          "category": "Малый город",
          "date": "15.07.2025 17:53:20"
        },
        {
          "num": "19",
          "certificate": "(Реком) 5300535",
          "main_score": "116",
          "extra_score": "79",
          "total_score": "195",
          "category": "Село",
          "date": "15.07.2025 13:38:56"
        },
        {
          "num": "20",
          "certificate": "(Реком) 5701671",
          "main_score": "114",
          "extra_score": "76",
          "total_score": "190",
          "category": "Село",
          "date": "14.07.2025 11:51:44"
        },
        {
          "num": "21",
          "certificate": "(Реком) 5710630",
          "main_score": "123",
          "extra_score": "61",
          "total_score": "184",
          "category": "Высокогорье",
          "date": "14.07.2025 12:05:33"
        },
        {
          "num": "22",
          "certificate": "(Реком) 5701494",
          "main_score": "121",
          "extra_score": "61",
          "total_score": "182",
          "category": "Малый город",
          "date": "14.07.2025 10:59:11"
        },
        {
          "num": "23",
          "certificate": "(Реком) 5700381",
          "main_score": "113",
          "extra_score": "65",
          "total_score": "178",
          "category": "Малый город",
          "date": "16.07.2025 12:52:39"
        },
        {
          "num": "24",
          "certificate": "(Реком) 5751562",
          "main_score": "112",
          "extra_score": "65",
          "total_score": "177",
          "category": "Село",
          "date": "16.07.2025 11:49:50"
        },
        {
          "num": "25",
          "certificate": "(Реком) 5701587",
          "main_score": "116",
          "extra_score": "61",
          "total_score": "177",
          "category": "Село",
          "date": "14.07.2025 12:31:27"
        },
        {
          "num": "26",
          "certificate": "(Реком) 5710048",
          "main_score": "113",
          "extra_score": "61",
          "total_score": "174",
          "category": "Высокогорье",
          "date": "16.07.2025 11:18:50"
        },
        {
          "num": "27",
          "certificate": "(Реком) 5760785",
          "main_score": "167",
          "extra_score": "0",
          "total_score": "167",
          "category": "Село",
          "date": "16.07.2025 13:41:45"
        },
        {
          "num": "28",
          "certificate": "(Реком) 5121161",
          "main_score": "161",
          "extra_score": "0",
          "total_score": "161",
          "category": "Село",
          "date": "16.07.2025 10:37:29"
        },
        {
          "num": "29",
          "certificate": "(Реком) 5761207",
          "main_score": "153",
          "extra_score": "0",
          "total_score": "153",
          "category": "Село",
          "date": "16.07.2025 00:09:18"
        },
        {
          "num": "30",
          "certificate": "(Реком) 5720004",
          "main_score": "151",
          "extra_score": "0",
          "total_score": "151",
          "category": "Село",
          "date": "15.07.2025 11:23:39"
        },
        {
          "num": "31",
          "certificate": "(Реком) 5750698",
          "main_score": "146",
          "extra_score": "0",
          "total_score": "146",
          "category": "Село",
          "date": "15.07.2025 14:51:39"
        },
        {
          "num": "32",
          "certificate": "(Реком) 5700322",
          "main_score": "140",
          "extra_score": "0",
          "total_score": "140",
          "category": "Малый город",
          "date": "16.07.2025 12:24:15"
        },
        {
          "num": "33",
          "certificate": "(Реком) 5731073",
          "main_score": "128",
          "extra_score": "0",
          "total_score": "128",
          "category": "Село",
          "date": "16.07.2025 12:57:57"
        },
        {
          "num": "34",
          "certificate": "(Реком) 5700499",
          "main_score": "126",
          "extra_score": "0",
          "total_score": "126",
          "category": "Малый город",
          "date": "14.07.2025 13:34:30"
        },
        {
          "num": "35",
          "certificate": "(Реком) 5760442",
          "main_score": "125",
          "extra_score": "0",
          "total_score": "125",
          "category": "Село",
          "date": "16.07.2025 09:31:32"
        },
        {
          "num": "36",
          "certificate": "(Реком) 5760575",
          "main_score": "123",
          "extra_score": "0",
          "total_score": "123",
          "category": "Село",
          "date": "15.07.2025 10:25:57"
        },
        {
          "num": "37",
          "certificate": "(Реком) 5410066",
          "main_score": "122",
          "extra_score": "0",
          "total_score": "122",
          "category": "Село",
          "date": "16.07.2025 11:45:40"
        },
        {
          "num": "38",
          "certificate": "(Реком) 5700870",
          "main_score": "119",
          "extra_score": "0",
          "total_score": "119",
          "category": "Малый город",
          "date": "15.07.2025 13:47:16"
        },
        {
          "num": "39",
          "certificate": "(Реком) 5750729",
          "main_score": "117",
          "extra_score": "0",
          "total_score": "117",
          "category": "Малый город",
          "date": "14.07.2025 17:32:58"
        },
        {
          "num": "40",
          "certificate": "(Реком) 5730630",
          "main_score": "116",
          "extra_score": "0",
          "total_score": "116",
          "category": "Село",
          "date": "16.07.2025 09:26:25"
        },
        {
          "num": "41",
          "certificate": "(Реком) 5710156",
          "main_score": "114",
          "extra_score": "0",
          "total_score": "114",
          "category": "Высокогорье",
          "date": "16.07.2025 13:52:50"
        },
        {
          "num": "42",
          "certificate": "(Реком) 5120959",
          "main_score": "112",
          "extra_score": "0",
          "total_score": "112",
          "category": "Высокогорье",
          "date": "14.07.2025 12:45:52"
        },
        {
          "num": "43",
          "certificate": "(Реком) 5720216",
          "main_score": "110",
          "extra_score": "0",
          "total_score": "110",
          "category": "Село",
          "date": "14.07.2025 11:44:22"
        }
      ]
    }
  ]
}