{
  "file": "personalcabinet_report_Ranjirb_i-6652_t-1.html",
  "university": "Ректор КНУ им. Ж. Баласагына",
  "director": "Чонтоев Д.Т.",
  "program": "Информационная безопасность [Информационная безопасность] ( Очная бакалавр)(Институт компьютерных технологии и искусственного интеллекта)",
  "plan": "План набора абитуриентов по специальности: 20 .",
  "recommended": "Рекомендовано: ______. Подтверждено: 13",
  "confirmed": null,
  "total_places": "1-тур. Итого вакантных мест: 20 . Зарегистрированных: 55 .",
  "total_registered": null,
  "admitted_count": 20,
  "not_admitted_count": 35,
  "tables": [
    {
      "header": "Бишкек: 8",
      "records": [
        {
          "num": "1",
          "certificate": "5221253",
          "note": null,
          "main_score": "190",
          "extra_score": "87",
          "total_score": "277",
          "category": "Бишкек",
          "date": "16.07.2025 13:46:37",
          "admitted": true
        },
        {
          "num": "2",
          "certificate": "5202211",
          "note": null,
          "main_score": "172",
          "extra_score": "76",
          "total_score": "248",
          "category": "Бишкек",
          "date": "16.07.2025 12:57:47",
          "admitted": true
        },
        {
          "num": "3",
          "certificate": "5200354",
          "note": null,
          "main_score": "153",
          "extra_score": "83",
          "total_score": "236",
          "category": "Бишкек",
          "date": "15.07.2025 12:39:59",
          "admitted": true
        },
        {
          "num": "4",
          "certificate": "5210742",
          "note": null,
          "main_score": "136",
          "extra_score": "68",
          "total_score": "204",
          "category": "Бишкек",
          "date": "16.07.2025 07:06:42",
          "admitted": true
        },
        {
          "num": "5",
          "certificate": "5231565",
          "note": null,
          "main_score": "124",
          "extra_score": "61",
          "total_score": "185",
          "category": "Бишкек",
          "date": "15.07.2025 12:10:07",
          "admitted": true
        },
        {
          "num": "6",
          "certificate": "5220075",
          "note": null,
          "main_score": "193",
          "extra_score": "0",
          "total_score": "193",
          "category": "Бишкек",
          "date": "15.07.2025 12:41:10",
          "admitted": true
        },
        {
          "num": "7",
          "certificate": "5212312",
          "note": null,
          "main_score": "173",
          "extra_score": "0",
          "total_score": "173",
          "category": "Бишкек",
          "date": "16.07.2025 10:35:51",
          "admitted": true
        },
        {
          "num": "8",
          "certificate": "5231663",
          "note": null,
          "main_score": "170",
          "extra_score": "0",
          "total_score": "170",
          "category": "Бишкек",
          "date": "16.07.2025 11:51:03",
          "admitted": true
        },
        {
          "num": "9",
          "certificate": "5231431",
          "note": null,
          "main_score": "167",
          "extra_score": "0",
          "total_score": "167",
          "category": "Бишкек",
          "date": "14.07.2025 13:09:21",
          "admitted": false
        },
        {
          "num": "10",
          "certificate": "5231445",
          "note": null,
          "main_score": "162",
          "extra_score": "0",
          "total_score": "162",
          "category": "Бишкек",
          "date": "16.07.2025 03:32:38",
          "admitted": false
        },
        {
          "num": "11",
          "certificate": "5201386",
          "note": null,
          "main_score": "160",
          "extra_score": "0",
          "total_score": "160",
          "category": "Бишкек",
          "date": "15.07.2025 21:43:53",
          "admitted": false
        },
        {
          "num": "12",
          "certificate": "5211565",
          "note": null,
          "main_score": "160",
          "extra_score": "0",
          "total_score": "160",
          "category": "Бишкек",
          "date": "15.07.2025 22:38:43",
          "admitted": false
        },
        {
          "num": "13",
          "certificate": "5210033",
          "note": null,
          "main_score": "153",
          "extra_score": "0",
          "total_score": "153",
          "category": "Бишкек",
          "date": "16.07.2025 09:17:26",
          "admitted": false
        },
        {
          "num": "14",
          "certificate": "5210234",
          "note": null,
          "main_score": "152",
          "extra_score": "0",
          "total_score": "152",
          "category": "Бишкек",
          "date": "14.07.2025 11:21:16",
          "admitted": false
        },
        {
          "num": "15",
          "certificate": "5232059",
          "note": null,
          "main_score": "152",
          "extra_score": "0",
          "total_score": "152",
          "category": "Бишкек",
          "date": "14.07.2025 14:34:56",
          "admitted": false
        },
        {
          "num": "16",
          "certificate": "5211204",
          "note": null,
          "main_score": "141",
          "extra_score": "0",
          "total_score": "141",
          "category": "Бишкек",
          "date": "14.07.2025 10:30:22",
          "admitted": false
        },
        {
          "num": "17",
          "certificate": "5207341",
          "note": null,
          "main_score": "134",
          "extra_score": "0",
          "total_score": "134",
          "category": "Бишкек",
          "date": "14.07.2025 10:57:12",
          "admitted": false
        },
        {
          "num": "18",
          "certificate": "5211400",
          "note": null,
          "main_score": "129",
          "extra_score": "0",
          "total_score": "129",
          "category": "Бишкек",
          "date": "15.07.2025 00:41:25",
          "admitted": false
        },
        {
          "num": "19",
          "certificate": "5202209",
          "note": null,
          "main_score": "124",
          "extra_score": "0",
          "total_score": "124",
          "category": "Бишкек",
          "date": "14.07.2025 18:48:29",
          "admitted": false
        },
        {
          "num": "20",
          "certificate": "5202174",
          "note": null,
          "main_score": "118",
          "extra_score": "0",
          "total_score": "118",
          "category": "Бишкек",
          "date": "15.07.2025 06:47:05",
          "admitted": false
        },
        {
          "num": "21",
          "certificate": "5200351",
          "note": null,
          "main_score": "116",
          "extra_score": "0",
          "total_score": "116",
          "category": "Бишкек",
          "date": "15.07.2025 01:29:52",
          "admitted": false
        },
        {
          "num": "22",
          "certificate": "5220428",
          "note": null,
          "main_score": "112",
          "extra_score": "0",
          "total_score": "112",
          "category": "Бишкек",
          "date": "14.07.2025 09:51:01",
          "admitted": false
        }
      ]
    },
    {
      "header": "Малый город: 5.09",
      "records": [
        {
          "num": "1",
          "certificate": "5370056",
          "note": null,
          "main_score": "205",
          "extra_score": "87",
          "total_score": "292",
          "category": "Малый город",
          "date": "16.07.2025 10:04:24",
          "admitted": true
        },
        {
          "num": "2",
          "certificate": "5100738",
          "note": null,
          "main_score": "158",
          "extra_score": "109",
          "total_score": "267",
          "category": "Малый город",
          "date": "16.07.2025 13:34:41",
          "admitted": true
        },
        {
          "num": "3",
          "certificate": "5540283",
          "note": null,
          "main_score": "183",
          "extra_score": "76",
          "total_score": "259",
          "category": "Малый город",
          "date": "16.07.2025 13:58:17",
          "admitted": true
        },
        {
          "num": "4",
          "certificate": "5371121",
          "note": null,
          "main_score": "155",
          "extra_score": "98",
          "total_score": "253",
          "category": "Малый город",
          "date": "15.07.2025 19:03:08",
          "admitted": true
        },
        {
          "num": "5",
          "certificate": "5530090",
          "note": null,
          "main_score": "159",
          "extra_score": "79",
          "total_score": "238",
          "category": "Малый город",
          "date": "15.07.2025 13:15:01",
          "admitted": true
        },
        {
          "num": "6",
          "certificate": "5110303",
          "note": null,
          "main_score": "143",
          "extra_score": "83",
          "total_score": "226",
          "category": "Малый город",
          "date": "15.07.2025 23:09:43",
          "admitted": false
        },
        {
          "num": "7",
          "certificate": "5140108",
          "note": null,
          "main_score": "144",
          "extra_score": "65",
          "total_score": "209",
          "category": "Малый город",
          "date": "16.07.2025 13:25:10",
          "admitted": false
        },
        {
          "num": "8",
          "certificate": "5540160",
          "note": null,
          "main_score": "128",
          "extra_score": "72",
          "total_score": "200",
          "category": "Малый город",
          "date": "16.07.2025 12:23:59",
          "admitted": false
        },
        {
          "num": "9",
          "certificate": "5310092",
          "note": null,
          "main_score": "162",
          "extra_score": "0",
          "total_score": "162",
          "category": "Малый город",
          "date": "14.07.2025 20:36:16",
          "admitted": false
        },
        {
          "num": "10",
          "certificate": "5120732",
          "note": null,
          "main_score": "153",
          "extra_score": "0",
          "total_score": "153",
          "category": "Малый город",
          "date": "14.07.2025 10:01:11",
          "admitted": false
        },
        {
          "num": "11",
          "certificate": "5120747",
          "note": null,
          "main_score": "145",
          "extra_score": "0",
          "total_score": "145",
          "category": "Малый город",
          "date": "14.07.2025 15:37:43",
          "admitted": false
        },
        {
          "num": "12",
          "certificate": "5510825",
          "note": null,
          "main_score": "138",
          "extra_score": "0",
          "total_score": "138",
          "category": "Малый город",
          "date": "14.07.2025 12:38:30",
          "admitted": false
        },
        {
          "num": "13",
          "certificate": "5540314",
          "note": null,
          "main_score": "134",
          "extra_score": "0",
          "total_score": "134",
          "category": "Малый город",
          "date": "14.07.2025 23:18:35",
          "admitted": false
        },
        {
          "num": "14",
          "certificate": "5960705",
          "note": null,
          "main_score": "133",
          "extra_score": "0",
          "total_score": "133",
          "category": "Малый город",
          "date": "16.07.2025 11:51:25",
          "admitted": false
        }
      ]
    },
    {
      "header": "Село: 4.36",
      "records": [
        {
          "num": "1",
          "certificate": "5520507",
          "note": null,
          "main_score": "169",
          "extra_score": "90",
          "total_score": "259",
          "category": "Село",
          "date": "16.07.2025 13:58:26",
          "admitted": true
        },
        {
          "num": "2",
          "certificate": "5340382",
          "note": null,
          "main_score": "172",
          "extra_score": "87",
          "total_score": "259",
          "category": "Село",
          "date": "16.07.2025 11:26:49",
          "admitted": true
        },
        {
          "num": "3",
          "certificate": "5950661",
          "note": null,
          "main_score": "164",
          "extra_score": "72",
          "total_score": "236",
          "category": "Село",
          "date": "14.07.2025 10:19:02",
          "admitted": true
        },
        {
          "num": "4",
          "certificate": "5120132",
          "note": null,
          "main_score": "156",
          "extra_score": "72",
          "total_score": "228",
          "category": "Село",
          "date": "16.07.2025 13:18:45",
          "admitted": true
        },
        {
          "num": "5",
          "certificate": "5360139",
          "note": null,
          "main_score": "165",
          "extra_score": "61",
          "total_score": "226",
          "category": "Село",
          "date": "15.07.2025 19:15:45",
          "admitted": false
        },
        {
          "num": "6",
          "certificate": "5750492",
          "note": null,
          "main_score": "158",
          "extra_score": "65",
          "total_score": "223",
          "category": "Село",
          "date": "15.07.2025 13:58:28",
          "admitted": false
        },
        {
          "num": "7",
          "certificate": "5970574",
          "note": null,
          "main_score": "137",
          "extra_score": "76",
          "total_score": "213",
          "category": "Село",
          "date": "16.07.2025 13:28:27",
          "admitted": false
        },
        {
          "num": "8",
          "certificate": "5550370",
          "note": null,
          "main_score": "141",
          "extra_score": "72",
          "total_score": "213",
          "category": "Село",
          "date": "14.07.2025 10:46:29",
          "admitted": false
        },
        {
          "num": "9",
          "certificate": "5930590",
          "note": null,
          "main_score": "170",
          "extra_score": "0",
          "total_score": "170",
          "category": "Село",
          "date": "14.07.2025 16:01:24",
          "admitted": false
        },
        {
          "num": "10",
          "certificate": "5380606",
          "note": null,
          "main_score": "123",
          "extra_score": "0",
          "total_score": "123",
          "category": "Село",
          "date": "14.07.2025 12:34:31",
          "admitted": false
        },
        {
          "num": "11",
          "certificate": "5127921",
          "note": null,
          "main_score": "119",
          "extra_score": "0",
          "total_score": "119",
          "category": "Село",
          "date": "14.07.2025 20:05:34",
          "admitted": false
        },
        {
          "num": "12",
          "certificate": "5520647",
          "note": null,
          "main_score": "117",
          "extra_score": "0",
          "total_score": "117",
          "category": "Село",
          "date": "15.07.2025 12:50:27",
          "admitted": false
        }
      ]
    },
    {
      "header": "Высокогорье: 2.55",
      "records": [
        {
          "num": "1",
          "certificate": "5600326",
          "note": null,
          "main_score": "157",
          "extra_score": "102",
          "total_score": "259",
          "category": "Высокогорье",
          "date": "16.07.2025 13:57:12",
          "admitted": true
        },
        {
          "num": "2",
          "certificate": "5620077",
          "note": null,
          "main_score": "148",
          "extra_score": "83",
          "total_score": "231",
          "category": "Высокогорье",
          "date": "14.07.2025 12:55:11",
          "admitted": true
        },
        {
          "num": "3",
          "certificate": "5207131",
          "note": null,
          "main_score": "145",
          "extra_score": "76",
          "total_score": "221",
          "category": "Высокогорье",
          "date": "16.07.2025 13:03:25",
          "admitted": true
        },
        {
          "num": "4",
          "certificate": "5610426",
          "note": null,
          "main_score": "161",
          "extra_score": "0",
          "total_score": "161",
          "category": "Высокогорье",
          "date": "16.07.2025 12:17:50",
          "admitted": false
        },
        {
          "num": "5",
          "certificate": "5630008",
          "note": null,
          "main_score": "141",
          "extra_score": "0",
          "total_score": "141",
          "category": "Высокогорье",
          "date": "14.07.2025 18:45:05",
          "admitted": false
        },
        {
          "num": "6",
          "certificate": "5550024",
          "note": null,
          "main_score": "116",
          "extra_score": "0",
          "total_score": "116",
          "category": "Высокогорье",
          "date": "14.07.2025 22:11:47",
          "admitted": false
        },
        {
          "num": "7",
          "certificate": "5222900",
          "note": "Дети, оставшиеся без попечения родителей",
          "main_score": "114",
          "extra_score": "0",
          "total_score": "114",
          "category": "Высокогорье",
          "date": "14.07.2025 16:46:27",
          "admitted": false
        }
      ]
    }
  ]
}