{
  "file": "personalcabinet_report_Ranjirb_i-5450_t-1.html",
  "university": "Первый проректор КТУ “Манас”",
  "director": "Ибраев Алмаз Орозакунович",
  "program": "Прикладная математика и информатика [Прикладная математика и информатика] ( Очная бакалавр)(Факультет естественных наук)",
  "plan": "План набора абитуриентов по специальности: 5 .",
  "recommended": "Рекомендовано: ______. Подтверждено: 3",
  "confirmed": null,
  "total_places": "1-тур. Итого вакантных мест: 5 . Зарегистрированных: 53 .",
  "total_registered": null,
  "tables": [
    {
      "header": "Бишкек: 1.42",
      "records": [
        {
          "num": "1",
          "certificate": "(Реком) 5221566",
          "main_score": "219",
          "extra_score": "142",
          "total_score": "361",
          "category": null,
          "date": "16.07.2025 00:01:43"
        },
        {
          "num": "2",
          "certificate": "5232254",
          "main_score": "224",
          "extra_score": "128",
          "total_score": "352",
          "category": null,
          "date": "16.07.2025 10:05:14"
        },
        {
          "num": "3",
          "certificate": "5200476",
          "main_score": "222",
          "extra_score": "124",
          "total_score": "346",
          "category": null,
          "date": "14.07.2025 15:59:58"
        },
        {
          "num": "4",
          "certificate": "5231768",
          "main_score": "205",
          "extra_score": "131",
          "total_score": "336",
          "category": null,
          "date": "15.07.2025 20:26:38"
        },
        {
          "num": "5",
          "certificate": "5221555",
          "main_score": "186",
          "extra_score": "139",
          "total_score": "325",
          "category": null,
          "date": "14.07.2025 11:30:23"
        },
        {
          "num": "6",
          "certificate": "5221066",
          "main_score": "215",
          "extra_score": "105",
          "total_score": "320",
          "category": null,
          "date": "14.07.2025 10:12:23"
        },
        {
          "num": "7",
          "certificate": "5200822",
          "main_score": "209",
          "extra_score": "109",
          "total_score": "318",
          "category": null,
          "date": "15.07.2025 20:34:37"
        },
        {
          "num": "8",
          "certificate": "5220706",
          "main_score": "208",
          "extra_score": "76",
          "total_score": "284",
          "category": null,
          "date": "14.07.2025 19:47:30"
        },
        {
          "num": "9",
          "certificate": "5207920",
          "main_score": "185",
          "extra_score": "98",
          "total_score": "283",
          "category": null,
          "date": "15.07.2025 07:27:13"
        },
        {
          "num": "10",
          "certificate": "5230934",
          "main_score": "195",
          "extra_score": "87",
          "total_score": "282",
          "category": null,
          "date": "14.07.2025 13:37:22"
        },
        {
          "num": "11",
          "certificate": "5200043",
          "main_score": "182",
          "extra_score": "72",
          "total_score": "254",
          "category": null,
          "date": "14.07.2025 13:41:50"
        },
        {
          "num": "12",
          "certificate": "5207727",
          "main_score": "176",
          "extra_score": "76",
          "total_score": "252",
          "category": null,
          "date": "16.07.2025 07:13:07"
        },
        {
          "num": "13",
          "certificate": "5221991",
          "main_score": "158",
          "extra_score": "90",
          "total_score": "248",
          "category": null,
          "date": "16.07.2025 13:28:45"
        },
        {
          "num": "14",
          "certificate": "5220716",
          "main_score": "156",
          "extra_score": "83",
          "total_score": "239",
          "category": null,
          "date": "14.07.2025 10:07:08"
        },
        {
          "num": "15",
          "certificate": "5231231",
          "main_score": "147",
          "extra_score": "61",
          "total_score": "208",
          "category": null,
          "date": "14.07.2025 09:54:45"
        }
      ]
    },
    {
      "header": "Малый город: 1.23",
      "records": [
        {
          "num": "1",
          "certificate": "(Реком) 5960412",
          "main_score": "212",
          "extra_score": "145",
          "total_score": "357",
          "category": null,
          "date": "15.07.2025 22:00:36"
        },
        {
          "num": "2",
          "certificate": "5212873",
          "main_score": "215",
          "extra_score": "142",
          "total_score": "357",
          "category": null,
          "date": "16.07.2025 11:15:31"
        },
        {
          "num": "3",
          "certificate": "5960402",
          "main_score": "211",
          "extra_score": "145",
          "total_score": "356",
          "category": null,
          "date": "16.07.2025 11:38:01"
        },
        {
          "num": "4",
          "certificate": "5340662",
          "main_score": "227",
          "extra_score": "124",
          "total_score": "351",
          "category": null,
          "date": "14.07.2025 11:00:18"
        },
        {
          "num": "5",
          "certificate": "5510428",
          "main_score": "202",
          "extra_score": "148",
          "total_score": "350",
          "category": null,
          "date": "15.07.2025 21:55:55"
        },
        {
          "num": "6",
          "certificate": "5700994",
          "main_score": "216",
          "extra_score": "116",
          "total_score": "332",
          "category": null,
          "date": "15.07.2025 16:57:15"
        },
        {
          "num": "7",
          "certificate": "5701828",
          "main_score": "201",
          "extra_score": "124",
          "total_score": "325",
          "category": null,
          "date": "14.07.2025 11:07:57"
        },
        {
          "num": "8",
          "certificate": "5761440",
          "main_score": "192",
          "extra_score": "109",
          "total_score": "301",
          "category": null,
          "date": "14.07.2025 09:42:25"
        },
        {
          "num": "9",
          "certificate": "5960445",
          "main_score": "183",
          "extra_score": "113",
          "total_score": "296",
          "category": null,
          "date": "15.07.2025 14:34:28"
        },
        {
          "num": "10",
          "certificate": "5370724",
          "main_score": "201",
          "extra_score": "90",
          "total_score": "291",
          "category": null,
          "date": "16.07.2025 13:54:16"
        },
        {
          "num": "11",
          "certificate": "5540162",
          "main_score": "169",
          "extra_score": "76",
          "total_score": "245",
          "category": null,
          "date": "16.07.2025 13:47:20"
        },
        {
          "num": "12",
          "certificate": "5350047",
          "main_score": "151",
          "extra_score": "72",
          "total_score": "223",
          "category": null,
          "date": "15.07.2025 20:40:23"
        },
        {
          "num": "13",
          "certificate": "5701451",
          "main_score": "136",
          "extra_score": "65",
          "total_score": "201",
          "category": null,
          "date": "14.07.2025 10:48:08"
        }
      ]
    },
    {
      "header": "Село: 1.79",
      "records": [
        {
          "num": "1",
          "certificate": "(Реком) 5120205",
          "main_score": "220",
          "extra_score": "145",
          "total_score": "365",
          "category": null,
          "date": "15.07.2025 17:16:00"
        },
        {
          "num": "2",
          "certificate": "(Реком) 5950310",
          "main_score": "223",
          "extra_score": "134",
          "total_score": "357",
          "category": null,
          "date": "16.07.2025 10:33:55"
        },
        {
          "num": "3",
          "certificate": "5120296",
          "main_score": "208",
          "extra_score": "142",
          "total_score": "350",
          "category": null,
          "date": "15.07.2025 15:27:15"
        },
        {
          "num": "4",
          "certificate": "5100487",
          "main_score": "199",
          "extra_score": "142",
          "total_score": "341",
          "category": null,
          "date": "14.07.2025 16:54:14"
        },
        {
          "num": "5",
          "certificate": "5120222",
          "main_score": "195",
          "extra_score": "139",
          "total_score": "334",
          "category": null,
          "date": "14.07.2025 11:18:25"
        },
        {
          "num": "6",
          "certificate": "5760652",
          "main_score": "218",
          "extra_score": "109",
          "total_score": "327",
          "category": null,
          "date": "15.07.2025 20:45:03"
        },
        {
          "num": "7",
          "certificate": "5810022",
          "main_score": "188",
          "extra_score": "128",
          "total_score": "316",
          "category": null,
          "date": "15.07.2025 13:08:56"
        },
        {
          "num": "8",
          "certificate": "5360369",
          "main_score": "202",
          "extra_score": "113",
          "total_score": "315",
          "category": null,
          "date": "14.07.2025 16:03:38"
        },
        {
          "num": "9",
          "certificate": "5100153",
          "main_score": "196",
          "extra_score": "116",
          "total_score": "312",
          "category": null,
          "date": "15.07.2025 14:35:04"
        },
        {
          "num": "10",
          "certificate": "5930255",
          "main_score": "198",
          "extra_score": "113",
          "total_score": "311",
          "category": null,
          "date": "14.07.2025 21:00:00"
        },
        {
          "num": "11",
          "certificate": "5930579",
          "main_score": "186",
          "extra_score": "120",
          "total_score": "306",
          "category": null,
          "date": "14.07.2025 14:32:25"
        },
        {
          "num": "12",
          "certificate": "5761425",
          "main_score": "178",
          "extra_score": "120",
          "total_score": "298",
          "category": null,
          "date": "14.07.2025 10:34:53"
        },
        {
          "num": "13",
          "certificate": "5560551",
          "main_score": "177",
          "extra_score": "102",
          "total_score": "279",
          "category": null,
          "date": "14.07.2025 13:19:07"
        },
        {
          "num": "14",
          "certificate": "5330058",
          "main_score": "183",
          "extra_score": "87",
          "total_score": "270",
          "category": null,
          "date": "14.07.2025 12:53:37"
        },
        {
          "num": "15",
          "certificate": "5900651",
          "main_score": "166",
          "extra_score": "102",
          "total_score": "268",
          "category": null,
          "date": "14.07.2025 09:49:04"
        },
        {
          "num": "16",
          "certificate": "5820134",
          "main_score": "180",
          "extra_score": "79",
          "total_score": "259",
          "category": null,
          "date": "14.07.2025 11:45:52"
        },
        {
          "num": "17",
          "certificate": "5970855",
          "main_score": "157",
          "extra_score": "65",
          "total_score": "222",
          "category": null,
          "date": "14.07.2025 09:56:12"
        },
        {
          "num": "18",
          "certificate": "5810368",
          "main_score": "144",
          "extra_score": "72",
          "total_score": "216",
          "category": null,
          "date": "16.07.2025 13:14:13"
        },
        {
          "num": "19",
          "certificate": "5720555",
          "main_score": "133",
          "extra_score": "79",
          "total_score": "212",
          "category": null,
          "date": "14.07.2025 10:18:52"
        }
      ]
    },
    {
      "header": "Высокогорье: 0.57",
      "records": [
        {
          "num": "1",
          "certificate": "(Реком) 5620032",
          "main_score": "212",
          "extra_score": "139",
          "total_score": "351",
          "category": null,
          "date": "16.07.2025 13:50:16"
        },
        {
          "num": "2",
          "certificate": "5710091",
          "main_score": "194",
          "extra_score": "142",
          "total_score": "336",
          "category": null,
          "date": "14.07.2025 22:31:35"
        },
        {
          "num": "3",
          "certificate": "5630478",
          "main_score": "195",
          "extra_score": "124",
          "total_score": "319",
          "category": null,
          "date": "16.07.2025 10:34:01"
        },
        {
          "num": "4",
          "certificate": "5650515",
          "main_score": "197",
          "extra_score": "120",
          "total_score": "317",
          "category": null,
          "date": "14.07.2025 10:50:10"
        },
        {
          "num": "5",
          "certificate": "5640065",
          "main_score": "202",
          "extra_score": "113",
          "total_score": "315",
          "category": null,
          "date": "14.07.2025 16:43:42"
        },
        {
          "num": "6",
          "certificate": "5630780",
          "main_score": "139",
          "extra_score": "102",
          "total_score": "241",
          "category": null,
          "date": "16.07.2025 11:51:06"
        }
      ]
    }
  ]
}