{
  "file": "personalcabinet_report_Ranjirk_i-114_t-1.html",
  "university": "Ректор КГТУ им. И.Раззакова",
  "director": "Чыныбаев М. К.",
  "program": "Информатика в здравоохранении и биомедицинская инженерия [Информатика в здравоохранении и биомедицинская инженерия] ( Очная бакалавр)(КГТИ)",
  "plan": "План набора абитуриентов по специальности: 20 .",
  "recommended": null,
  "confirmed": null,
  "total_places": "1-тур. Итого вакантных мест: 20 . Зарегистрированных: 7 .",
  "total_registered": null,
  "admitted_count": 7,
  "not_admitted_count": 0,
  "tables": [
    {
      "header": null,
      "records": [
        {
          "num": "1",
          "certificate": "5530639",
          "note": null,
          "main_score": "153",
          "extra_score": "65",
          "total_score": "218",
          "category": null,
          "date": "14.07.2025 20:37:09",
          "admitted": true
        },
        {
          "num": "2",
          "certificate": "5232083",
          "note": null,
          "main_score": "140",
          "extra_score": "72",
          "total_score": "212",
          "category": null,
          "date": "14.07.2025 23:38:56",
          "admitted": true
        },
        {
          "num": "3",
          "certificate": "5500496",
          "note": null,
          "main_score": "188",
          "extra_score": "0",
          "total_score": "188",
          "category": null,
          "date": "16.07.2025 13:32:54",
          "admitted": true
        },
        {
          "num": "4",
          "certificate": "5220264",
          "note": null,
          "main_score": "138",
          "extra_score": "0",
          "total_score": "138",
          "category": null,
          "date": "14.07.2025 12:47:32",
          "admitted": true
        },
        {
          "num": "5",
          "certificate": "5400167",
          "note": null,
          "main_score": "135",
          "extra_score": "0",
          "total_score": "135",
          "category": null,
          "date": "16.07.2025 12:48:54",
          "admitted": true
        },
        {
          "num": "6",
          "certificate": "5221155",
          "note": null,
          "main_score": "120",
          "extra_score": "0",
          "total_score": "120",
          "category": null,
          "date": "14.07.2025 22:47:40",
          "admitted": true
        },
        {
          "num": "7",
          "certificate": "5210690",
          "note": null,
          "main_score": "120",
          "extra_score": "0",
          "total_score": "120",
          "category": null,
          "date": "15.07.2025 22:11:45",
          "admitted": true
        }
      ]
    }
  ]
}