{
  "file": "personalcabinet_report_Ranjirk_i-7220_t-1.html",
  "university": "Ректор КГУ им.И.Арабаева",
  "director": "Абдраева А.Т.",
  "program": "Туризм [Туризм] (Заочное)(ИЯ)",
  "plan": "План набора абитуриентов по специальности: 20 .",
  "recommended": null,
  "confirmed": null,
  "total_places": "1-тур. Итого вакантных мест: 20 . Зарегистрированных: 4 .",
  "total_registered": null,
  "admitted_count": 4,
  "not_admitted_count": 0,
  "tables": [
    {
      "header": null,
      "records": [
        {
          "num": "1",
          "certificate": "5203034",
          "note": null,
          "main_score": "168",
          "extra_score": "102",
          "total_score": "270",
          "category": null,
          "date": "14.07.2025 21:13:00",
          "admitted": true
        },
        {
          "num": "2",
          "certificate": "5221992",
          "note": null,
          "main_score": "162",
          "extra_score": "94",
          "total_score": "256",
          "category": null,
          "date": "16.07.2025 13:04:17",
          "admitted": true
        },
        {
          "num": "3",
          "certificate": "5650492",
          "note": null,
          "main_score": "134",
          "extra_score": "0",
          "total_score": "134",
          "category": null,
          "date": "16.07.2025 12:43:05",
          "admitted": true
        },
        {
          "num": "4",
          "certificate": "5207154",
          "note": null,
          "main_score": "117",
          "extra_score": "0",
          "total_score": "117",
          "category": null,
          "date": "14.07.2025 13:33:59",
          "admitted": true
        }
      ]
    }
  ]
}